{
	"metaDataVersion": "1.0.0",
	"category": "com.microchip.ide.project",
	"content": {
		"metaDataVersion": "1.1.0",
		"name": "com.microchip.mcu32.mplabx.project.usb_apps_device_hid_basic_remote_wakeup_sam_e54_xpro",
		"version": "3.4.0",
		"displayName": "HID Basic Remote basic Example (hid_basic) Example for SAM D5x/E5x Family",
		"projectName": "hid_basic_remote_wakeup_sam_e54_xpro",
		"shortDescription": "This application creates a USB HID Device that enumerates as a custom USB HID device on the USB host PC. The device allows the status of a device and having a remote wakeup feature.",
		"ide": {
			"name": "MPLABX",
			"semverRange": ">=6.00.0"
		},
		"compiler": [
			{
				"name": "XC32",
				"semverRange": ">=4.1.0"
			}
		],
		"dfp": {
			"name": "SAME54_DFP",
			"semverRange": "^3.6.95"
		},
		"configurator": {
			"name": "MCC",
			"semverRange": ">=5.1.1"
		},
		"device": {
			"metaDataVersion": "1.0.0",
			"category": "com.microchip.portal.contentRef",
			"content": {
				"metaDataVersion": "1.0.0",
				"category": "com.microchip.device",
				"name": "ATSAME54P20A",
				"versionRange": "*"
			}
		},
		"author": "Microchip",
		"subcategories": [
			[
				"Development Kit", "SAM E54 Xplained Pro Evaluation Kit"
			],
			[
				"Harmony", "Middleware", "USB", "DEVICE_HID_BASIC_REMOTE_WAKEUP"
			],
			[
				"Middleware", "USB", "DEVICE_HID_BASIC_REMOTE_WAKEUP"
			]
		],
		"peripherals": [
			"USB"
		],
		"keywords": [
			"MHC",
			"Harmony",
			"Middleware",
			"USB",
			"ATSAME54P20A",
			"SAM D5x/E5x Family",
			"USB"
		],
		"additionalData": {
			"longDescription": {
				"metaDataVersion": "1.0.0",
				"category": "com.microchip.portal.fileRef",
				"content": {
					"metaDataVersion": "1.0.0",
					"fileName": "./../../readme.md",
					"mimeType": "text/markdown"
				}
			}
		}
	}
}